Workbook

Sheet Assumptions
A1: TREASURY AGENT - FINANCIAL MODEL
A3: CUSTOMER ACQUISITION
A4: Month 1 New Customers | B4: 3 | C4: Pilot phase, accelerator intros
A5: Monthly Customer Growth M1-M3 | B5: 0.15 | C5: 15% MoM growth in early phase
A6: Monthly Customer Growth M4-M12 | B6: 0.1 | C6: 10% MoM growth as market matures
A8: REVENUE MODEL
A9: Avg Monthly SaaS (per customer) | B9: 1000 | C9: Starter $500 + Pro $1.5k average
A10: Avg Settlement Volume (per customer) | B10: 25000000 | C10: $25M annual = $2.1M monthly avg
A11: Settlement Spread (basis points) | B11: 0.0075 | C11: 7.5 bps on stablecoin routing
A12: AI Agent Premium (per customer/month) | B12: 75 | C12: Optional advanced treasury features
A13: AI Premium Adoption Rate | B13: 0.25 | C13: 25% of customers opt for premium
A15: OPERATING COSTS
A16: Month 1 Headcount | B16: 5 | C16: 2 eng, 1 AI/ML, 1 BD, 1 ops
A17: Avg Salary (per employee/month) | B17: 10000 | C17: Blended average including taxes/benefits
A18: Monthly Headcount Growth | B18: 0.08 | C18: Add staff as revenue scales
A19: Infrastructure (per month) | B19: 2000 | C19: Solana RPC nodes, API infrastructure
A20: Marketing/Sales (% of revenue) | B20: 0.2 | C20: Warm intros reduce CAC
A21: Other OpEx (% of revenue) | B21: 0.15 | C21: Legal, compliance, admin, overhead
A23: RETENTION
A24: Monthly Churn Rate | B24: 0.05 | C24: 5% MoM, 95% retention rate

Sheet 12-Month Projections
A1: TREASURY AGENT - 12 MONTH PROJECTIONS
A3: Month | B3: M1 | C3: M2 | D3: M3 | E3: M4 | F3: M5 | G3: M6 | H3: M7 | I3: M8 | J3: M9 | K3: M10 | L3: M11 | M3: M12
A4: CUSTOMERS
A5: Ending Customers | B5: 3 | C5: 4 | D5: 5 | E5: 6 | F5: 7 | G5: 8 | H5: 9 | I5: 10 | J5: 11 | K5: 12 | L5: 13 | M5: 14
A7: REVENUE
A8: SaaS Subscription Revenue | B8: =B5*Assumptions!B8 | C8: =C5*Assumptions!B8 | D8: =D5*Assumptions!B8 | E8: =E5*Assumptions!B8 | F8: =F5*Assumptions!B8 | G8: =G5*Assumptions!B8 | H8: =H5*Assumptions!B8 | I8: =I5*Assumptions!B8 | J8: =J5*Assumptions!B8 | K8: =K5*Assumptions!B8 | L8: =L5*Assumptions!B8 | M8: =M5*Assumptions!B8
A9: Settlement Spread Revenue | B9: =B5*Assumptions!B10*Assumptions!B11 | C9: =C5*Assumptions!B10*Assumptions!B11 | D9: =D5*Assumptions!B10*Assumptions!B11 | E9: =E5*Assumptions!B10*Assumptions!B11 | F9: =F5*Assumptions!B10*Assumptions!B11 | G9: =G5*Assumptions!B10*Assumptions!B11 | H9: =H5*Assumptions!B10*Assumptions!B11 | I9: =I5*Assumptions!B10*Assumptions!B11 | J9: =J5*Assumptions!B10*Assumptions!B11 | K9: =K5*Assumptions!B10*Assumptions!B11 | L9: =L5*Assumptions!B10*Assumptions!B11 | M9: =M5*Assumptions!B10*Assumptions!B11
A10: AI Agent Premium Revenue | B10: =B5*Assumptions!B13*Assumptions!B14 | C10: =C5*Assumptions!B13*Assumptions!B14 | D10: =D5*Assumptions!B13*Assumptions!B14 | E10: =E5*Assumptions!B13*Assumptions!B14 | F10: =F5*Assumptions!B13*Assumptions!B14 | G10: =G5*Assumptions!B13*Assumptions!B14 | H10: =H5*Assumptions!B13*Assumptions!B14 | I10: =I5*Assumptions!B13*Assumptions!B14 | J10: =J5*Assumptions!B13*Assumptions!B14 | K10: =K5*Assumptions!B13*Assumptions!B14 | L10: =L5*Assumptions!B13*Assumptions!B14 | M10: =M5*Assumptions!B13*Assumptions!B14
A11: Total Monthly Revenue | B11: =B8+B9+B10 | C11: =C8+C9+C10 | D11: =D8+D9+D10 | E11: =E8+E9+E10 | F11: =F8+F9+F10 | G11: =G8+G9+G10 | H11: =H8+H9+H10 | I11: =I8+I9+I10 | ... M11: =M8+M9+M10
A13: OPERATING COSTS
A14: Salary Expense | B14: =Assumptions!B15*Assumptions!B16 | C14: =B14*(1+Assumptions!B17) | D14: =C14*(1+Assumptions!B17) | E14: =D14*(1+Assumptions!B17) | F14: =E14*(1+Assumptions!B17) | G14: =F14*(1+Assumptions!B17) | H14: =G14*(1+Assumptions!B17) | I14: =H14*(1+Assumptions!B17) | J14: =I14*(1+Assumptions!B17) | K14: =J14*(1+Assumptions!B17) | L14: =K14*(1+Assumptions!B17) | M14: =L14*(1+Assumptions!B17)
A15: Infrastructure Costs | B15: =Assumptions!B19 | C15: =Assumptions!B19 | D15: =Assumptions!B19 | E15: =Assumptions!B19 | F15: =Assumptions!B19 | G15: =Assumptions!B19 | H15: =Assumptions!B19 | I15: =Assumptions!B19 | J15: =Assumptions!B19 | K15: =Assumptions!B19 | L15: =Assumptions!B19 | M15: =Assumptions!B19
A16: Marketing & Sales | B16: =B8*Assumptions!B20 | C16: =C8*Assumptions!B20 | D16: =D8*Assumptions!B20 | E16: =E8*Assumptions!B20 | F16: =F8*Assumptions!B20 | G16: =G8*Assumptions!B20 | H16: =H8*Assumptions!B20 | I16: =I8*Assumptions!B20 | J16: =J8*Assumptions!B20 | K16: =K8*Assumptions!B20 | L16: =L8*Assumptions!B20 | M16: =M8*Assumptions!B20
A17: Other Operating Expenses | B17: =B8*Assumptions!B21 | C17: =C8*Assumptions!B21 | D17: =D8*Assumptions!B21 | E17: =E8*Assumptions!B21 | F17: =F8*Assumptions!B21 | G17: =G8*Assumptions!B21 | H17: =H8*Assumptions!B21 | I17: =I8*Assumptions!B21 | J17: =J8*Assumptions!B21 | K17: =K8*Assumptions!B21 | L17: =L8*Assumptions!B21 | M17: =M8*Assumptions!B21
A18: Total Operating Costs | B18: =B14+B15+B16+B17 | C18: =C14+C15+C16+C17 | D18: =D14+D15+D16+D17 | E18: =E14+E15+E16+E17 | F18: =F14+F15+F16+F17 | G18: =G14+G15+G16+G17 | H18: =H14+H15+H16+H17 | I18: =I14+I15+I16+I17 | ... M18: =M14+M15+M16+M17
A20: PROFITABILITY
A21: Gross Profit | B21: =B9-B18 | C21: =C9-C18 | D21: =D9-D18 | E21: =E9-E18 | F21: =F9-F18 | G21: =G9-G18 | H21: =H9-H18 | I21: =I9-I18 | ... M21: =M9-M18
A22: Gross Margin % | B22: =IFERROR(B21/B9,0) | C22: =IFERROR(C21/C9,0) | D22: =IFERROR(D21/D9,0) | E22: =IFERROR(E21/E9,0) | F22: =IFERROR(F21/F9,0) | G22: =IFERROR(G21/G9,0) | H22: =IFERROR(H21/H9,0) | I22: =IFERROR(I21/I9,0) | ... M22: =IFERROR(M21/M9,0)
A23: Operating Profit | B23: =B21 | C23: =C21 | D23: =D21 | E23: =E21 | F23: =F21 | G23: =G21 | H23: =H21 | I23: =I21 | ... M23: =M21

Sheet Unit Economics
A1: UNIT ECONOMICS
A3: Monthly Recurring Revenue (per customer) | B3: =Assumptions!B8+(Assumptions!B10*Assumptions!B11)+(Assumptions!B13*Assumptions!B14) | C3: Avg SaaS + settlement + AI premium
A4: Annual Customer Lifetime Value | B4: =B1*12*(1-Assumptions!B22)^12 | C4: MRR × 12 months accounting for churn
A5: Estimated CAC | B5: 3500 | C5: Typical warm intro cost in APAC
A6: LTV/CAC Ratio | B6: =B2/B3 | C6: Ideal: 3.0x or higher
A7: Payback Period (months) | B7: =IFERROR(B3/B1,0) | C7: Months to recover customer acquisition cost
A9: Month 12 ARR | B9: ='12-Month Projections'!M18*12 | C9: Month 12 monthly revenue × 12
A10: Month 12 Customer Count | B10: ='12-Month Projections'!M4 | C10: Ending customers in month 12
A11: Avg ACV (Annual Contract Value) | B11: =IFERROR(B8/B9,0) | C11: ARR / customer count
A13: Year 1 Gross Profit | B13: =SUM('12-Month Projections'!B15:M15) | C13: Sum of monthly gross profit
A14: Runway (months at seed) [500k] | B14: =IFERROR(500000/AVERAGE('12-Month Projections'!B20:M20),0) | C14: Seed funding / avg monthly OpEx

Sheet Roadmap
A1: TREASURY AGENT - 12 MONTH ROADMAP & MILESTONES
A3: Initiative | B3: M1 | C3: M2 | D3: M3 | E3: M4 | F3: M5 | G3: M6 | H3: M7 | I3: M8 | J3: M9 | K3: M10 | L3: M11 | M3: M12
A4: MVP Build & Validation | B4: ● | C4: ●
A5: Market Pilot (India) | D5: ● | E5: ● | F5: ●
A6: Compliance & Legal Setup | B6: ● | C6: ● | D6: ● | E6: ● | F6: ● | G6: ●
A7: Solana Integration | B7: ● | C7: ● | D7: ● | E7: ●
A8: AI Agent Development | C8: ● | D8: ● | E8: ● | F8: ● | G8: ● | H8: ● | I8: ●
A9: APAC Expansion | G9: ● | H9: ● | I9: ● | J9: ●
A10: LatAm Preparation | I10: ● | J10: ● | K10: ● | L10: ● | M10: ●
A11: Series A Prep | J11: ● | K11: ● | L11: ● | M11: ●
A14: KEY MILESTONES
A15: M1-M2 | B15: MVP Ready for Pilot
A16: M3 | B16: First 10 Customers Onboarded
A17: M5 | B17: India Pilot Targets 50+ Customers
A18: M6 | B18: Series A Preparation Begins
A19: M7 | B19: APAC Launch (Philippines)
A20: M12 | B20: Series A Fundraise Close
